.DS_Store
callystio/__init__.py
callystio/__main__.py
callystio/cli.py
callystio/config.py
callystio/site.py
callystio/builders/__init__.py
callystio/builders/builder.py
callystio/builders/index.py
callystio/builders/notebook.py
callystio/builders/page.py
callystio/builders/static.py
callystio/loaders/__init__.py
callystio/loaders/loader.py
callystio/loaders/markdown.py
callystio/loaders/notebook.py
callystio/loaders/static.py
callystio-1.0.0.dist-info/LICENSE
callystio-1.0.0.dist-info/METADATA
callystio-1.0.0.dist-info/WHEEL
callystio-1.0.0.dist-info/entry_points.txt
callystio-1.0.0.dist-info/top_level.txt
callystio-1.0.0.dist-info/RECORD
